{
  "id": "header",
  "label": "Header",
  "format": "custom",
  "repeatable": false,
  "status": true,
  "json": {
    "Main": {
      "title": {
        "type": "Text",
        "config": {
          "label": "Title",
          "placeholder": ""
        }
      },
      "navigation": {
        "type": "Group",
        "config": {
          "label": "Navigation",
          "fields": {
            "link": {
              "type": "Link",
              "config": {
                "label": "Link",
                "placeholder": "",
                "select": null
              }
            },
            "label": {
              "type": "Text",
              "config": {
                "label": "Label",
                "placeholder": ""
              }
            }
          }
        }
      }
    }
  }
}
